sp_utils/__init__.py
sp_utils/common.py
sp_utils-0.0.2.dist-info/METADATA
sp_utils-0.0.2.dist-info/RECORD
sp_utils-0.0.2.dist-info/WHEEL
sp_utils-0.0.2.dist-info/top_level.txt
