Metadata-Version: 2.1
Name: sp-utils
Version: 0.0.2
Summary: A small example package
Home-page: https://github.com/ospoon
Author: Spoon
Author-email: zxin088@gmail.com
License: UNKNOWN
Platform: UNKNOWN
Classifier: Programming Language :: Python :: 3
Classifier: License :: OSI Approved :: MIT License
Classifier: Operating System :: OS Independent
